[
    {
        "name": "Gavotte",
        "file": "Gavotte",
        "audioFiles": ["Gavotte_Violin_Only", "Gavotte_With_Harpsicord"],
        "price": 5,
        "composer": "J. B. Lully",
        "category": "Classical",
        "instruments": ["violin"]
    },
    {
        "name": "A Whole New World",
        "file": "A_Whole_New_World",
        "audioFiles": ["A_Whole_New_World"],
        "price": 5,
        "composer": "Alan Menken",
        "category": "Movie",
        "instruments": ["violin"]
    },
    {
        "name": "The Round Song",
        "file": "The_Round_Song",
        "audioFiles": ["The_Round_Song"],
        "price": 5,
        "composer": "Jaden Day",
        "category": "Classical",
        "instruments": ["violin"]
    },
    {
        "name": "He's a Pirate",
        "file": "Hes_a_Pirate",
        "audioFiles": "",
        "price": 5,
        "composer": "Klaus Badelt",
        "category": "Movie",
        "instruments": ["violin"]
    },
    {
        "name": "Go the Distance",
        "file": "Go_the_Distance",
        "audioFiles": ["Go_the_Distance"],
        "price": 5,
        "composer": "Alan Menken",
        "category": "Movie",
        "instruments": ["violin"]
    },
    {
        "name": "Fiddle Song",
        "file": "Fiddle_Song",
        "audioFiles": "",
        "price": 3,
        "composer": "Composer Unknown",
        "category": "Fiddle",
        "instruments": ["violin"]
    },
    {
        "name": "Fall is Coming: Part 1",
        "file": "Fall_is_Coming_1",
        "audioFiles": ["FIC1-violin1-count","FIC1-violin2-count","FIC1-both-count"],
        "price": 1,
        "composer": "Jaden Day",
        "category": "Classical",
        "instruments": ["violin"]
    },
    {
        "name": "Fall is Coming: Part 2",
        "file": "Fall_is_Coming_2",
        "audioFiles": ["FIC2-violin1-count","FIC2-violin2-count","FIC2-both-count","FIC-full-song-violin1-count","FIC-full-song-violin2-count","FIC-full-song-both-count"],
        "price": 1,
        "composer": "Jaden Day",
        "category": "Classical",
        "instruments": ["violin"]
    },
    {
        "name": "I am a Child of God: Both",
        "file": "I_am_a_Child_of_God_Both",
        "audioFiles": ["I_am_a_Child_of_God", "Child_of_God_Violin_counting", "Child_of_God_Piano_counting"],
        "price": 1,
        "composer": "Mildred T. Pettit",
        "category": "Religious",
        "instruments": ["violin"]
    },
    {
        "name": "I am a Child of God: Violin 1",
        "file": "I_am_a_Child_of_God_Violin1",
        "audioFiles": "",
        "price": 1,
        "composer": "Mildred T. Pettit",
        "category": "Religious",
        "instruments": ["violin"]
    },
    {
        "name": "I am a Child of God: Violin 2",
        "file": "I_am_a_Child_of_God_Violin2",
        "audioFiles": "",
        "price": 1,
        "composer": "Mildred T. Pettit",
        "category": "Religious",
        "instruments": ["violin"]
    }
]
